setup.py
gaussian_binomial_dist_test/Binomialdistribution.py
gaussian_binomial_dist_test/Gaussiandistribution.py
gaussian_binomial_dist_test/Generaldistribution.py
gaussian_binomial_dist_test/__init__.py
gaussian_binomial_dist_test.egg-info/PKG-INFO
gaussian_binomial_dist_test.egg-info/SOURCES.txt
gaussian_binomial_dist_test.egg-info/dependency_links.txt
gaussian_binomial_dist_test.egg-info/not-zip-safe
gaussian_binomial_dist_test.egg-info/top_level.txt