Metadata-Version: 1.0
Name: gaussian-binomial-dist-test
Version: 0.1
Summary: Gaussian distributions
Home-page: UNKNOWN
Author: Tran Nguyen
Author-email: UNKNOWN
License: UNKNOWN
Platform: UNKNOWN
